tessel/__init__.py
tessel/py.typed
tessel/sdk.py
tessel-0.0.1a0.dist-info/METADATA
tessel-0.0.1a0.dist-info/WHEEL
tessel-0.0.1a0.dist-info/RECORD
