Metadata-Version: 2.4
Name: tessel
Version: 0.0.1a0
Summary: Library for capturing and syncing neural representations for use with the Tessel AI arcana platform
Project-URL: Homepage, https://tessel.ai
Author-email: Tessel AI <support@tessel.ai>
License: MIT
Keywords: Deep Learning,Explainability,Model Hardening,Monitoring
Classifier: Development Status :: 3 - Alpha
Classifier: Intended Audience :: Developers
Classifier: Intended Audience :: Science/Research
Classifier: License :: OSI Approved :: MIT License
Classifier: Operating System :: OS Independent
Classifier: Programming Language :: Python :: 3
Classifier: Programming Language :: Python :: 3.12
Classifier: Programming Language :: Python :: 3.13
Classifier: Topic :: Scientific/Engineering :: Artificial Intelligence
Classifier: Topic :: Software Development :: Libraries :: Python Modules
Classifier: Topic :: System :: Monitoring
Requires-Python: >=3.12
